Metadata-Version: 1.0
Name: imdbpie-async
Version: 1.0.0
Summary: An async fork to imdb-pie
Home-page: https://github.com/hifumibot/imdb-pie
Author: MaT1g3R
Author-email: UNKNOWN
License: MIT
Platform: UNKNOWN
